nonebot_plugin_draw/__init__.py
nonebot_plugin_draw/message.py
nonebot_plugin_draw-0.1.2.dist-info/METADATA
nonebot_plugin_draw-0.1.2.dist-info/WHEEL
nonebot_plugin_draw-0.1.2.dist-info/top_level.txt
nonebot_plugin_draw-0.1.2.dist-info/RECORD
