Metadata-Version: 2.1
Name: nonebot-plugin-draw
Version: 0.1.2
Summary: draw lots
Home-page: https://github.com/bingganhe123/nonebot_plugin_draw
Author: bingganhe123
Author-email: 3143799170@qq.com
License: MIT Licence
Platform: UNKNOWN
Requires-Python: >=3.9, <4
Requires-Dist: nonebot2 (>=2.0.0b1)
